[
  {
    "id": 1,
    "title": "Spaghetti Bolognese",
    "summary": "A classic Italian pasta dish with rich meat sauce.",
    "description": "Delicious spaghetti with homemade bolognese sauce, simmered to perfection.",
    "ingredients": ["Spaghetti", "Minced meat", "Tomato sauce", "Onion", "Garlic", "Olive oil"],
    "image": "https://source.unsplash.com/600x400/?spaghetti"
  },
  {
    "id": 2,
    "title": "Chicken Curry",
    "summary": "Spicy and flavorful chicken curry.",
    "description": "A hearty curry dish with tender chicken and a blend of spices.",
    "ingredients": ["Chicken", "Curry powder", "Onion", "Tomato", "Coconut milk"],
    "image": "https://source.unsplash.com/600x400/?curry"
  }
]
